Metadata-Version: 1.0
Name: my-package-kk
Version: 1.2.0
Summary: hi fi super star
Home-page: UNKNOWN
Author: kk12pt
Author-email: spam@12pt.pl
License: UNKNOWN
Platform: UNKNOWN
